affine_image/__init__.py
affine_image/image_3d.py
affine_image-0.1.0.dist-info/LICENSE
affine_image-0.1.0.dist-info/METADATA
affine_image-0.1.0.dist-info/WHEEL
affine_image-0.1.0.dist-info/RECORD
