Metadata-Version: 2.1
Name: affine-image
Version: 0.1.0
Summary: Pure NumPy implementation of affine image transformations
Home-page: https://github.com/codingfisch/affine_image.np
License: MIT
Author: codingfisch
Author-email: l_fisc17@wwu.de
Requires-Python: >=3.8,<4.0
Classifier: Intended Audience :: Science/Research
Classifier: License :: OSI Approved :: MIT License
Classifier: Operating System :: OS Independent
Classifier: Programming Language :: Python :: 3
Classifier: Programming Language :: Python :: 3.8
Classifier: Programming Language :: Python :: 3.9
Classifier: Programming Language :: Python :: 3.10
Classifier: Programming Language :: Python :: 3.11
Requires-Dist: numpy
Project-URL: Repository, https://github.com/codingfisch/affine_image.np
